flask_meter/__init__.py
flask_meter/flask_meter.py
flask_meter/git.py
flask_meter/version.py
Flask_Meter-1.1.2.dist-info/AUTHORS.rst
Flask_Meter-1.1.2.dist-info/LICENSE
Flask_Meter-1.1.2.dist-info/METADATA
Flask_Meter-1.1.2.dist-info/WHEEL
Flask_Meter-1.1.2.dist-info/top_level.txt
Flask_Meter-1.1.2.dist-info/RECORD
