Metadata-Version: 2.1
Name: Flask-Meter
Version: 1.1.2
Summary: Flask-Meter adds a healthcheck endpoint for Flask apps.
Author-email: Herman Singh <kartstig@gmail.com>
Maintainer-email: Herman Singh <kartstig@gmail.com>
License: MIT License
Project-URL: Donate, https://github.com/sponsors/Kartstig/dashboard
Project-URL: Documentation, https://flask.palletsprojects.com/
Project-URL: Source Code, https://github.com/Kartstig/flask-meter
Project-URL: Issue Tracker, https://github.com/Kartstig/flask-meter/issues
Classifier: Development Status :: 5 - Production/Stable
Classifier: Environment :: Web Environment
Classifier: Intended Audience :: Developers
Classifier: License :: OSI Approved :: MIT License
Classifier: Natural Language :: English
Classifier: Operating System :: MacOS :: MacOS X
Classifier: Operating System :: Microsoft :: Windows
Classifier: Operating System :: POSIX :: Linux
Classifier: Programming Language :: Python :: 3.5
Classifier: Programming Language :: Python :: 3.6
Classifier: Programming Language :: Python :: 3.7
Classifier: Programming Language :: Python :: 3.8
Classifier: Programming Language :: Python :: 3.9
Classifier: Programming Language :: Python :: 3.10
Classifier: Programming Language :: Python :: 3.11
Classifier: Topic :: Software Development :: Libraries :: Python Modules
Requires-Python: >3.7
License-File: LICENSE
License-File: AUTHORS.rst
Requires-Dist: Flask (>=0.12)
